dictor/__init__.py
dictor-0.1.2.dist-info/LICENSE
dictor-0.1.2.dist-info/METADATA
dictor-0.1.2.dist-info/WHEEL
dictor-0.1.2.dist-info/top_level.txt
dictor-0.1.2.dist-info/zip-safe
dictor-0.1.2.dist-info/RECORD
