Metadata-Version: 2.1
Name: dictor
Version: 0.1.2
Summary: an elegant dictionary and JSON handler
Home-page: https://github.com/perfecto25/dictor
Author: mike.reider
Author-email: mike.reider@gmail.com
License: MIT
Platform: UNKNOWN
